elit_tokenizer/__init__.py
elit_tokenizer/demo.py
elit_tokenizer/tokenizer.py
elit_tokenizer/util.py
elit_tokenizer/resources/__init__.py
elit_tokenizer/resources/english_abbreviation_period.txt
elit_tokenizer/resources/english_apostrophe_front.txt
elit_tokenizer/resources/english_concat_words.txt
elit_tokenizer/resources/english_hyphen_prefix.txt
elit_tokenizer/resources/english_hyphen_suffix.txt
elit_tokenizer/tests/__init__.py
elit_tokenizer/tests/conftest.py
elit_tokenizer/tests/test_tokenizer.py
elit_tokenizer-1.0.dist-info/LICENSE
elit_tokenizer-1.0.dist-info/METADATA
elit_tokenizer-1.0.dist-info/WHEEL
elit_tokenizer-1.0.dist-info/top_level.txt
elit_tokenizer-1.0.dist-info/RECORD
